include/fftw3.h
psnr_hvsm.libs/libgomp-a34b3233.so.1.0.0
psnr_hvsm/compute_all_metrics.py
psnr_hvsm/dct.cpp
psnr_hvsm/_psnr_hvsm.cpython-39-x86_64-linux-gnu.so
psnr_hvsm/CMakeLists.txt
psnr_hvsm/compare_results.py
psnr_hvsm/dct.h
psnr_hvsm/tid2013_metrics.py
psnr_hvsm/__main__.py
psnr_hvsm/psnr_hvsm.h
psnr_hvsm/psnr_hvsm_pybind11.cpp
psnr_hvsm/hvsm.h
psnr_hvsm/__init__.py
psnr_hvsm/psnr_hvsm.cpp
psnr_hvsm/torch/psnr_hma.py
psnr_hvsm/torch/psnr_hvsm.py
psnr_hvsm/torch/psnr.py
psnr_hvsm/torch/bt601.py
psnr_hvsm/torch/__init__.py
psnr_hvsm/numpy/psnr_hma.py
psnr_hvsm/numpy/psnr_hvsm.py
psnr_hvsm/numpy/psnr.py
psnr_hvsm/numpy/bt601.py
psnr_hvsm/numpy/__init__.py
lib64/libfftw3.a
lib64/cmake/fftw3/FFTW3ConfigVersion.cmake
lib64/cmake/fftw3/FFTW3LibraryDepends-relwithdebinfo.cmake
lib64/cmake/fftw3/FFTW3LibraryDepends.cmake
lib64/cmake/fftw3/FFTW3Config.cmake
lib64/pkgconfig/fftw3.pc
psnr_hvsm-0.2.4.dist-info/RECORD
psnr_hvsm-0.2.4.dist-info/WHEEL
psnr_hvsm-0.2.4.dist-info/METADATA
psnr_hvsm-0.2.4.dist-info/licenses/LICENSE
