Metadata-Version: 2.1
Name: psnr_hvsm
Version: 0.2.4
Summary: Accelerated implementations of the PSNR-HVS, PSNR-HVS-M, PSNR-HA and PSNR-HMA image metrics for NumPy and PyTorch
Keywords: psnr hvs video image metric pytorch
Author-Email: Karol Trojanowski <trojanowski.ifuj@gmail.com>
License: MIT
Classifier: Development Status :: 4 - Beta
Classifier: Programming Language :: Python :: 3
Classifier: Programming Language :: Python :: 3.7
Classifier: Programming Language :: Python :: 3.8
Classifier: Programming Language :: Python :: 3.9
Classifier: Programming Language :: Python :: 3.10
Classifier: Programming Language :: Python :: 3.11
Classifier: Programming Language :: Python :: 3.12
Classifier: Programming Language :: C++
Classifier: Operating System :: POSIX :: Linux
Classifier: Operating System :: Microsoft :: Windows
Classifier: License :: OSI Approved :: GNU General Public License v3 (GPLv3)
Classifier: Intended Audience :: Science/Research
Classifier: Topic :: Scientific/Engineering :: Image Processing
Project-URL: Homepage, https://github.com/lyckantropen/psnr_hvsm
Requires-Python: <4,>=3.7
Requires-Dist: numpy<2,>=1.18
Requires-Dist: msvc-runtime>=14; platform_system == "Windows"
Requires-Dist: pytest; extra == "tests"
Requires-Dist: scipy; extra == "tests"
Requires-Dist: imageio; extra == "tests"
Requires-Dist: imageio; extra == "command-line"
Requires-Dist: tqdm; extra == "command-line"
Requires-Dist: torch; extra == "torch"
Requires-Dist: torch-dct>=0.1.6; extra == "torch"
Provides-Extra: tests
Provides-Extra: command-line
Provides-Extra: torch
